{
  "manifestVersion": "3.2",
  "proxies": [
    {
      "address": "0x3a4B0F96DD8AE3BF6d1B9aE1049f25D3eCd107d9",
      "txHash": "0x25277450908a8128e8a48407153091c51830efc79be87283369da7304b7874aa",
      "kind": "transparent"
    },
    {
      "address": "0x9fbef89b59CdaB9feD504BFB3ecC6b23A92785B1",
      "txHash": "0x917a548d7fdd5bb8acb03171866a0c1ef651cbf5f40c73bb10c99646b39b67aa",
      "kind": "transparent"
    },
    {
      "address": "0xFBAec7b60207A680196612510D411197B02b4dCC",
      "txHash": "0x6c45e233bab0a616a10c6d58c1d0637e97973a6d15a251513e76b86dc6b44eec",
      "kind": "transparent"
    }
  ],
  "impls": {
    "b182255893d5a77ebd3be00d05f59d613dc068402663406903096b2084cd5c86": {
      "address": "0x16F62cab69EAE24b97026b79788Cd64288E34cac",
      "txHash": "0x323d0269fdec2bb30cec7fa4891997890254683af80802755a680f1e55463124",
      "layout": {
        "solcVersion": "0.8.24",
        "storage": [
          {
            "label": "value",
            "offset": 0,
            "slot": "0",
            "type": "t_uint256",
            "contract": "UpgradableContractV1",
            "src": "contracts/UpgradableContractV1.sol:7"
          }
        ],
        "types": {
          "t_bool": {
            "label": "bool",
            "numberOfBytes": "1"
          },
          "t_struct(InitializableStorage)10_storage": {
            "label": "struct Initializable.InitializableStorage",
            "members": [
              {
                "label": "_initialized",
                "type": "t_uint64",
                "offset": 0,
                "slot": "0"
              },
              {
                "label": "_initializing",
                "type": "t_bool",
                "offset": 8,
                "slot": "0"
              }
            ],
            "numberOfBytes": "32"
          },
          "t_uint64": {
            "label": "uint64",
            "numberOfBytes": "8"
          },
          "t_uint256": {
            "label": "uint256",
            "numberOfBytes": "32"
          }
        },
        "namespaces": {
          "erc7201:openzeppelin.storage.Initializable": [
            {
              "contract": "Initializable",
              "label": "_initialized",
              "type": "t_uint64",
              "src": "@openzeppelin/contracts-upgradeable/proxy/utils/Initializable.sol:69",
              "offset": 0,
              "slot": "0"
            },
            {
              "contract": "Initializable",
              "label": "_initializing",
              "type": "t_bool",
              "src": "@openzeppelin/contracts-upgradeable/proxy/utils/Initializable.sol:73",
              "offset": 8,
              "slot": "0"
            }
          ]
        }
      }
    },
    "511801b96176ba1768870691be0c68bfdf808866b456341f94c80fc15e25f338": {
      "address": "0x64dE84658c31040b0fE168870883F4318f817803",
      "txHash": "0xee321525dbf161fd80084eac8c0b8d9fd8bcbf72814594c15d4838a4e02071c3",
      "layout": {
        "solcVersion": "0.8.24",
        "storage": [
          {
            "label": "value",
            "offset": 0,
            "slot": "0",
            "type": "t_uint256",
            "contract": "UpgradableContractV1",
            "src": "contracts/UpgradableContractV1.sol:7"
          }
        ],
        "types": {
          "t_bool": {
            "label": "bool",
            "numberOfBytes": "1"
          },
          "t_struct(InitializableStorage)10_storage": {
            "label": "struct Initializable.InitializableStorage",
            "members": [
              {
                "label": "_initialized",
                "type": "t_uint64",
                "offset": 0,
                "slot": "0"
              },
              {
                "label": "_initializing",
                "type": "t_bool",
                "offset": 8,
                "slot": "0"
              }
            ],
            "numberOfBytes": "32"
          },
          "t_uint64": {
            "label": "uint64",
            "numberOfBytes": "8"
          },
          "t_uint256": {
            "label": "uint256",
            "numberOfBytes": "32"
          }
        },
        "namespaces": {
          "erc7201:openzeppelin.storage.Initializable": [
            {
              "contract": "Initializable",
              "label": "_initialized",
              "type": "t_uint64",
              "src": "@openzeppelin/contracts-upgradeable/proxy/utils/Initializable.sol:69",
              "offset": 0,
              "slot": "0"
            },
            {
              "contract": "Initializable",
              "label": "_initializing",
              "type": "t_bool",
              "src": "@openzeppelin/contracts-upgradeable/proxy/utils/Initializable.sol:73",
              "offset": 8,
              "slot": "0"
            }
          ]
        }
      }
    },
    "9bb542018852231b75685a9cece1c6cb108ebf7a1cefad035a27c31ad0b67473": {
      "address": "0xA99fFA2ae6ab26b136284e965ecD8e94714f7056",
      "txHash": "0x1e8e83f6430e5b519c8c807352755d144692826e116ef77bed873a0efce9d6e1",
      "layout": {
        "solcVersion": "0.8.24",
        "storage": [
          {
            "label": "value",
            "offset": 0,
            "slot": "0",
            "type": "t_uint256",
            "contract": "UpgradableContractV3",
            "src": "contracts/UpgradableContractV3.sol:7"
          }
        ],
        "types": {
          "t_bool": {
            "label": "bool",
            "numberOfBytes": "1"
          },
          "t_struct(InitializableStorage)10_storage": {
            "label": "struct Initializable.InitializableStorage",
            "members": [
              {
                "label": "_initialized",
                "type": "t_uint64",
                "offset": 0,
                "slot": "0"
              },
              {
                "label": "_initializing",
                "type": "t_bool",
                "offset": 8,
                "slot": "0"
              }
            ],
            "numberOfBytes": "32"
          },
          "t_uint64": {
            "label": "uint64",
            "numberOfBytes": "8"
          },
          "t_uint256": {
            "label": "uint256",
            "numberOfBytes": "32"
          }
        },
        "namespaces": {
          "erc7201:openzeppelin.storage.Initializable": [
            {
              "contract": "Initializable",
              "label": "_initialized",
              "type": "t_uint64",
              "src": "@openzeppelin/contracts-upgradeable/proxy/utils/Initializable.sol:69",
              "offset": 0,
              "slot": "0"
            },
            {
              "contract": "Initializable",
              "label": "_initializing",
              "type": "t_bool",
              "src": "@openzeppelin/contracts-upgradeable/proxy/utils/Initializable.sol:73",
              "offset": 8,
              "slot": "0"
            }
          ]
        }
      }
    },
    "240092d8fdacba37edfbdd6e82888d07dd12b2de0e5ab51375ea410d12c7dfcb": {
      "address": "0x330Ba67662BE929e6Be1aB1B76a3896786e38b8e",
      "txHash": "0xebd3980dbb2c4a0a91e8a2345f2aa87a0c5ac25b898f5e442069b013f8c25ec4",
      "layout": {
        "solcVersion": "0.8.24",
        "storage": [
          {
            "label": "value",
            "offset": 0,
            "slot": "0",
            "type": "t_uint256",
            "contract": "Box",
            "src": "contracts/Box.sol:8"
          }
        ],
        "types": {
          "t_uint256": {
            "label": "uint256",
            "numberOfBytes": "32"
          }
        },
        "namespaces": {}
      }
    },
    "d048cca7298c769e7576f1ca403e8ac7cd7942c491258996ab206662207c47b1": {
      "address": "0xEC489beDf7f52D0280CdBcdBAb5ca37310D034D0",
      "txHash": "0xd82b27e25fbe89800dd12802dd8103ad6ffbf4baf14824d1853422058766d91d",
      "layout": {
        "solcVersion": "0.8.24",
        "storage": [
          {
            "label": "value",
            "offset": 0,
            "slot": "0",
            "type": "t_uint256",
            "contract": "BoxV2",
            "src": "contracts/BoxV2.sol:8"
          }
        ],
        "types": {
          "t_uint256": {
            "label": "uint256",
            "numberOfBytes": "32"
          }
        },
        "namespaces": {}
      }
    }
  }
}
